promptcheck/__init__.py
promptcheck/cli/init_cmd.py
promptcheck/cli/run_cmd.py
promptcheck/core/metrics.py
promptcheck/core/providers.py
promptcheck/core/runner.py
promptcheck/core/schemas.py
promptcheck/main.py
promptcheck/utils/file_handler.py
promptcheck/utils/logging_utils.py
promptcheck-0.1.0b6.dist-info/LICENSE
promptcheck-0.1.0b6.dist-info/LICENSE_NOTICE.md
promptcheck-0.1.0b6.dist-info/METADATA
promptcheck-0.1.0b6.dist-info/WHEEL
promptcheck-0.1.0b6.dist-info/entry_points.txt
promptcheck-0.1.0b6.dist-info/RECORD
