Metadata-Version: 2.3
Name: promptcheck
Version: 0.1.0b6
Summary: CI-first prompt testing framework for LLMs
Author: PromptCheck Labs
Author-email: support@promptcheckllm.com
Requires-Python: >=3.11,<4.0
Classifier: Programming Language :: Python :: 3
Classifier: Programming Language :: Python :: 3.11
Classifier: Programming Language :: Python :: 3.12
Classifier: Programming Language :: Python :: 3.13
Provides-Extra: bleu
Requires-Dist: groq (>=0.24.0,<0.25.0)
Requires-Dist: nltk (>=3.9.1,<4.0.0) ; extra == "bleu"
Requires-Dist: openai (>=1.78.1,<2.0.0)
Requires-Dist: pydantic (>=2.11.4,<3.0.0)
Requires-Dist: pyyaml (>=6.0.2,<7.0.0)
Requires-Dist: rouge-score (>=0.1.2,<0.2.0)
Requires-Dist: tenacity (>=9.1.2,<10.0.0)
Requires-Dist: typer (>=0.15.4,<0.16.0)
